{
"36136": {
    "visible": 1,
    "x": 932,
    "y": 330
},
"36137": {
    "visible": 1,
    "x": 932,
    "y": 330
},
"36138": {
    "visible": 1,
    "x": 932,
    "y": 330
},
"36139": {
    "visible": 1,
    "x": 932,
    "y": 330
},
"36140": {
    "visible": 1,
    "x": 932,
    "y": 330
},
"36141": {
    "visible": 1,
    "x": 932,
    "y": 330
},
"36142": {
    "visible": 1,
    "x": 932,
    "y": 330
},
"36143": {
    "visible": 1,
    "x": 928,
    "y": 332
},
"36144": {
    "visible": 1,
    "x": 925,
    "y": 330
},
"36145": {
    "visible": 1,
    "x": 922,
    "y": 330
},
"36146": {
    "visible": 1,
    "x": 919,
    "y": 334
},
"36147": {
    "visible": 1,
    "x": 913,
    "y": 341
},
"36148": {
    "visible": 1,
    "x": 911,
    "y": 343
},
"36149": {
    "visible": 1,
    "x": 911,
    "y": 345
},
"36150": {
    "visible": 1,
    "x": 907,
    "y": 354
},
"36151": {
    "visible": 1,
    "x": 904,
    "y": 365
},
"36152": {
    "visible": 1,
    "x": 902,
    "y": 379
},
"36153": {
    "visible": 1,
    "x": 896,
    "y": 392
},
"36154": {
    "visible": 1,
    "x": 887,
    "y": 316
},
"36155": {
    "visible": 1,
    "x": 879,
    "y": 241
},
"36156": {
    "visible": 1,
    "x": 871,
    "y": 165
},
"36157": {
    "visible": 1,
    "x": 863,
    "y": 90
},
"36158": {
    "visible": 1,
    "x": 855,
    "y": 15
},
"36159": {
    "visible": 1,
    "x": 874,
    "y": 51
},
"36160": {
    "visible": 1,
    "x": 894,
    "y": 87
},
"36161": {
    "visible": 1,
    "x": 913,
    "y": 124
},
"36162": {
    "visible": 1,
    "x": 933,
    "y": 160
},
"36163": {
    "visible": 1,
    "x": 952,
    "y": 196
},
"36164": {
    "visible": 1,
    "x": 972,
    "y": 233
},
"36165": {
    "visible": 1,
    "x": 991,
    "y": 269
},
"36166": {
    "visible": 1,
    "x": 1011,
    "y": 306
},
"36167": {
    "visible": 1,
    "x": 1010,
    "y": 309
},
"36168": {
    "visible": 1,
    "x": 1031,
    "y": 300
},
"36169": {
    "visible": 1,
    "x": 1024,
    "y": 314
},
"36170": {
    "visible": 1,
    "x": 1017,
    "y": 328
},
"36171": {
    "visible": 1,
    "x": 1011,
    "y": 343
},
"36172": {
    "visible": 1,
    "x": 1004,
    "y": 357
},
"36173": {
    "visible": 1,
    "x": 998,
    "y": 371
},
"36174": {
    "visible": 1,
    "x": 992,
    "y": 386
},
"36175": {
    "visible": 1,
    "x": 980,
    "y": 372
},
"36176": {
    "visible": 1,
    "x": 969,
    "y": 359
},
"36177": {
    "visible": 1,
    "x": 957,
    "y": 346
},
"36178": {
    "visible": 1,
    "x": 946,
    "y": 333
},
"36179": {
    "visible": 1,
    "x": 934,
    "y": 319
},
"36180": {
    "visible": 1,
    "x": 923,
    "y": 306
},
"36181": {
    "visible": 1,
    "x": 911,
    "y": 293
},
"36182": {
    "visible": 1,
    "x": 900,
    "y": 279
},
"36183": {
    "visible": 1,
    "x": 888,
    "y": 266
},
"36184": {
    "visible": 1,
    "x": 877,
    "y": 253
},
"36185": {
    "visible": 1,
    "x": 865,
    "y": 240
},
"36186": {
    "visible": 1,
    "x": 854,
    "y": 226
},
"36187": {
    "visible": 1,
    "x": 842,
    "y": 213
},
"36188": {
    "visible": 1,
    "x": 831,
    "y": 200
},
"36189": {
    "visible": 1,
    "x": 820,
    "y": 187
},
"36190": {
    "visible": 1,
    "x": 808,
    "y": 174
},
"36191": {
    "visible": 1,
    "x": 797,
    "y": 160
},
"36192": {
    "visible": 1,
    "x": 785,
    "y": 147
},
"36193": {
    "visible": 1,
    "x": 774,
    "y": 134
},
"36194": {
    "visible": 1,
    "x": 762,
    "y": 120
},
"36195": {
    "visible": 1,
    "x": 751,
    "y": 107
},
"36196": {
    "visible": 1,
    "x": 739,
    "y": 94
},
"36197": {
    "visible": 1,
    "x": 728,
    "y": 81
},
"36198": {
    "visible": 1,
    "x": 716,
    "y": 68
},
"36199": {
    "visible": 1,
    "x": 705,
    "y": 54
},
"36200": {
    "visible": 1,
    "x": 693,
    "y": 41
},
"36201": {
    "visible": 1,
    "x": 682,
    "y": 28
},
"36202": {
    "visible": 1,
    "x": 671,
    "y": 15
},
"36203": {
    "visible": 1,
    "x": 669,
    "y": 17
},
"36204": {
    "visible": 1,
    "x": 667,
    "y": 54
},
"36205": {
    "visible": 1,
    "x": 665,
    "y": 92
},
"36206": {
    "visible": 1,
    "x": 662,
    "y": 124
},
"36207": {
    "visible": 1,
    "x": 660,
    "y": 156
},
"36208": {
    "visible": 1,
    "x": 658,
    "y": 188
},
"36209": {
    "visible": 1,
    "x": 655,
    "y": 220
},
"36210": {
    "visible": 1,
    "x": 653,
    "y": 252
},
"36211": {
    "visible": 1,
    "x": 651,
    "y": 284
},
"36212": {
    "visible": 1,
    "x": 649,
    "y": 317
},
"36213": {
    "visible": 1,
    "x": 647,
    "y": 354
},
"36214": {
    "visible": 1,
    "x": 646,
    "y": 379
},
"36215": {
    "visible": 1,
    "x": 645,
    "y": 405
},
"36216": {
    "visible": 1,
    "x": 645,
    "y": 431
},
"36217": {
    "visible": 1,
    "x": 643,
    "y": 469
},
"36218": {
    "visible": 1,
    "x": 655,
    "y": 333
},
"36219": {
    "visible": 1,
    "x": 667,
    "y": 334
},
"36220": {
    "visible": 1,
    "x": 680,
    "y": 452
},
"36221": {
    "visible": 1,
    "x": 680,
    "y": 452
},
"36222": {
    "visible": 1,
    "x": 699,
    "y": 410
},
"36223": {
    "visible": 1,
    "x": 714,
    "y": 384
},
"36224": {
    "visible": 1,
    "x": 722,
    "y": 367
},
"36225": {
    "visible": 1,
    "x": 729,
    "y": 354
},
"36226": {
    "visible": 1,
    "x": 737,
    "y": 347
},
"36227": {
    "visible": 1,
    "x": 737,
    "y": 347
},
"36228": {
    "visible": 1,
    "x": 740,
    "y": 339
},
"36229": {
    "visible": 1,
    "x": 744,
    "y": 337
},
"36230": {
    "visible": 1,
    "x": 752,
    "y": 335
},
"36231": {
    "visible": 1,
    "x": 755,
    "y": 337
},
"36232": {
    "visible": 1,
    "x": 759,
    "y": 339
},
"36233": {
    "visible": 1,
    "x": 759,
    "y": 339
},
"36234": {
    "visible": 1,
    "x": 761,
    "y": 343
},
"36235": {
    "visible": 1,
    "x": 763,
    "y": 349
},
"36236": {
    "visible": 1,
    "x": 765,
    "y": 360
},
"36237": {
    "visible": 1,
    "x": 757,
    "y": 365
},
"36238": {
    "visible": 1,
    "x": 753,
    "y": 377
},
"36239": {
    "visible": 1,
    "x": 754,
    "y": 377
},
"36240": {
    "visible": 1,
    "x": 752,
    "y": 382
},
"36241": {
    "visible": 1,
    "x": 748,
    "y": 394
},
"36242": {
    "visible": 1,
    "x": 744,
    "y": 407
},
"36243": {
    "visible": 1,
    "x": 740,
    "y": 420
},
"36244": {
    "visible": 1,
    "x": 737,
    "y": 435
},
"36245": {
    "visible": 1,
    "x": 737,
    "y": 435
},
"36246": {
    "visible": 1,
    "x": 733,
    "y": 448
},
"36247": {
    "visible": 1,
    "x": 729,
    "y": 465
},
"36248": {
    "visible": 1,
    "x": 729,
    "y": 482
},
"36249": {
    "visible": 1,
    "x": 724,
    "y": 502
},
"36250": {
    "visible": 1,
    "x": 722,
    "y": 523
},
"36251": {
    "visible": 1,
    "x": 722,
    "y": 523
},
"36252": {
    "visible": 1,
    "x": 718,
    "y": 544
},
"36253": {
    "visible": 1,
    "x": 714,
    "y": 566
},
"36254": {
    "visible": 1,
    "x": 717,
    "y": 544
},
"36255": {
    "visible": 1,
    "x": 721,
    "y": 503
},
"36256": {
    "visible": 1,
    "x": 725,
    "y": 455
},
"36257": {
    "visible": 1,
    "x": 729,
    "y": 399
},
"36258": {
    "visible": 1,
    "x": 733,
    "y": 335
},
"36259": {
    "visible": 1,
    "x": 737,
    "y": 230
},
"36260": {
    "visible": 1,
    "x": 740,
    "y": 202
},
"36261": {
    "visible": 1,
    "x": 742,
    "y": 178
},
"36262": {
    "visible": 1,
    "x": 744,
    "y": 159
},
"36263": {
    "visible": 1,
    "x": 744,
    "y": 157
},
"36264": {
    "visible": 1,
    "x": 744,
    "y": 146
},
"36265": {
    "visible": 1,
    "x": 748,
    "y": 135
},
"36266": {
    "visible": 1,
    "x": 750,
    "y": 125
},
"36267": {
    "visible": 1,
    "x": 752,
    "y": 120
},
"36268": {
    "visible": 1,
    "x": 752,
    "y": 116
},
"36269": {
    "visible": 1,
    "x": 752,
    "y": 116
},
"36270": {
    "visible": 1,
    "x": 755,
    "y": 114
},
"36271": {
    "visible": 1,
    "x": 755,
    "y": 114
},
"36272": {
    "visible": 1,
    "x": 759,
    "y": 118
},
"36273": {
    "visible": 1,
    "x": 759,
    "y": 122
},
"36274": {
    "visible": 1,
    "x": 763,
    "y": 125
},
"36275": {
    "visible": 1,
    "x": 763,
    "y": 125
},
"36276": {
    "visible": 1,
    "x": 763,
    "y": 133
},
"36277": {
    "visible": 1,
    "x": 767,
    "y": 140
},
"36278": {
    "visible": 1,
    "x": 767,
    "y": 148
},
"36279": {
    "visible": 1,
    "x": 770,
    "y": 159
},
"36280": {
    "visible": 1,
    "x": 774,
    "y": 172
},
"36281": {
    "visible": 1,
    "x": 774,
    "y": 174
},
"36282": {
    "visible": 1,
    "x": 774,
    "y": 184
},
"36283": {
    "visible": 1,
    "x": 791,
    "y": 216
},
"36284": {
    "visible": 1,
    "x": 808,
    "y": 249
},
"36285": {
    "visible": 1,
    "x": 825,
    "y": 282
},
"36286": {
    "visible": 1,
    "x": 842,
    "y": 314
},
"36287": {
    "visible": 1,
    "x": 859,
    "y": 347
},
"36288": {
    "visible": 1,
    "x": 876,
    "y": 379
},
"36289": {
    "visible": 1,
    "x": 893,
    "y": 412
},
"36290": {
    "visible": 1,
    "x": 910,
    "y": 445
},
"36291": {
    "visible": 1,
    "x": 928,
    "y": 478
},
"36292": {
    "visible": 1,
    "x": 939,
    "y": 506
},
"36293": {
    "visible": 1,
    "x": 939,
    "y": 508
},
"36294": {
    "visible": 1,
    "x": 947,
    "y": 534
},
"36295": {
    "visible": 1,
    "x": 958,
    "y": 568
},
"36296": {
    "visible": 1,
    "x": 964,
    "y": 592
},
"36297": {
    "visible": 1,
    "x": 995,
    "y": 482
},
"36298": {
    "visible": 1,
    "x": 1018,
    "y": 420
},
"36299": {
    "visible": 1,
    "x": 1016,
    "y": 416
},
"36300": {
    "visible": 1,
    "x": 1037,
    "y": 360
},
"36301": {
    "visible": 1,
    "x": 1048,
    "y": 317
},
"36302": {
    "visible": 1,
    "x": 1059,
    "y": 287
},
"36303": {
    "visible": 1,
    "x": 1067,
    "y": 259
},
"36304": {
    "visible": 1,
    "x": 1076,
    "y": 236
},
"36305": {
    "visible": 1,
    "x": 1076,
    "y": 234
},
"36306": {
    "visible": 1,
    "x": 1082,
    "y": 219
},
"36307": {
    "visible": 1,
    "x": 1089,
    "y": 208
},
"36308": {
    "visible": 1,
    "x": 1095,
    "y": 197
},
"36309": {
    "visible": 1,
    "x": 1100,
    "y": 189
},
"36310": {
    "visible": 1,
    "x": 1104,
    "y": 182
},
"36311": {
    "visible": 1,
    "x": 1104,
    "y": 182
},
"36312": {
    "visible": 1,
    "x": 1112,
    "y": 178
},
"36313": {
    "visible": 1,
    "x": 1114,
    "y": 178
},
"36314": {
    "visible": 1,
    "x": 1119,
    "y": 178
},
"36315": {
    "visible": 1,
    "x": 1121,
    "y": 182
},
"36316": {
    "visible": 1,
    "x": 1127,
    "y": 185
},
"36317": {
    "visible": 1,
    "x": 1127,
    "y": 185
},
"36318": {
    "visible": 1,
    "x": 1129,
    "y": 189
},
"36319": {
    "visible": 1,
    "x": 1130,
    "y": 197
},
"36320": {
    "visible": 1,
    "x": 1134,
    "y": 206
},
"36321": {
    "visible": 1,
    "x": 1138,
    "y": 215
},
"36322": {
    "visible": 1,
    "x": 1138,
    "y": 226
},
"36323": {
    "visible": 1,
    "x": 1138,
    "y": 226
},
"36324": {
    "visible": 1,
    "x": 1138,
    "y": 226
},
"36325": {
    "visible": 1,
    "x": 1138,
    "y": 234
},
"36326": {
    "visible": 1,
    "x": 1134,
    "y": 234
},
"36327": {
    "visible": 1,
    "x": 1127,
    "y": 232
},
"36328": {
    "visible": 1,
    "x": 1125,
    "y": 238
},
"36329": {
    "visible": 1,
    "x": 1125,
    "y": 238
},
"36330": {
    "visible": 1,
    "x": 1123,
    "y": 244
},
"36331": {
    "visible": 1,
    "x": 1119,
    "y": 253
},
"36332": {
    "visible": 1,
    "x": 1117,
    "y": 262
},
"36333": {
    "visible": 1,
    "x": 1112,
    "y": 274
},
"36334": {
    "visible": 1,
    "x": 1112,
    "y": 287
},
"36335": {
    "visible": 1,
    "x": 1112,
    "y": 287
},
"36336": {
    "visible": 1,
    "x": 1108,
    "y": 302
},
"36337": {
    "visible": 1,
    "x": 1104,
    "y": 319
},
"36338": {
    "visible": 1,
    "x": 1100,
    "y": 335
},
"36339": {
    "visible": 1,
    "x": 1097,
    "y": 352
},
"36340": {
    "visible": 1,
    "x": 1095,
    "y": 370
},
"36341": {
    "visible": 1,
    "x": 1093,
    "y": 384
},
"36342": {
    "visible": 1,
    "x": 1091,
    "y": 398
},
"36343": {
    "visible": 1,
    "x": 1089,
    "y": 422
},
"36344": {
    "visible": 1,
    "x": 1085,
    "y": 442
},
"36345": {
    "visible": 1,
    "x": 1082,
    "y": 467
},
"36346": {
    "visible": 1,
    "x": 1080,
    "y": 493
},
"36347": {
    "visible": 1,
    "x": 1080,
    "y": 493
},
"36348": {
    "visible": 1,
    "x": 1057,
    "y": 451
},
"36349": {
    "visible": 1,
    "x": 1035,
    "y": 418
},
"36350": {
    "visible": 1,
    "x": 1013,
    "y": 383
},
"36351": {
    "visible": 1,
    "x": 991,
    "y": 347
},
"36352": {
    "visible": 1,
    "x": 969,
    "y": 307
},
"36353": {
    "visible": 1,
    "x": 967,
    "y": 307
},
"36354": {
    "visible": 1,
    "x": 947,
    "y": 272
},
"36355": {
    "visible": 1,
    "x": 932,
    "y": 245
},
"36356": {
    "visible": 1,
    "x": 920,
    "y": 223
},
"36357": {
    "visible": 1,
    "x": 907,
    "y": 204
},
"36358": {
    "visible": 1,
    "x": 894,
    "y": 186
},
"36359": {
    "visible": 1,
    "x": 894,
    "y": 184
},
"36360": {
    "visible": 1,
    "x": 887,
    "y": 178
},
"36361": {
    "visible": 1,
    "x": 877,
    "y": 169
},
"36362": {
    "visible": 1,
    "x": 868,
    "y": 163
},
"36363": {
    "visible": 1,
    "x": 860,
    "y": 157
},
"36364": {
    "visible": 1,
    "x": 855,
    "y": 155
},
"36365": {
    "visible": 1,
    "x": 853,
    "y": 155
},
"36366": {
    "visible": 1,
    "x": 847,
    "y": 155
},
"36367": {
    "visible": 1,
    "x": 842,
    "y": 155
},
"36368": {
    "visible": 1,
    "x": 842,
    "y": 155
},
"36369": {
    "visible": 1,
    "x": 857,
    "y": 142
},
"36370": {
    "visible": 1,
    "x": 872,
    "y": 133
},
"36371": {
    "visible": 1,
    "x": 872,
    "y": 131
},
"36372": {
    "visible": 1,
    "x": 883,
    "y": 124
},
"36373": {
    "visible": 1,
    "x": 892,
    "y": 122
},
"36374": {
    "visible": 1,
    "x": 902,
    "y": 120
},
"36375": {
    "visible": 1,
    "x": 909,
    "y": 120
},
"36376": {
    "visible": 1,
    "x": 917,
    "y": 122
},
"36377": {
    "visible": 1,
    "x": 917,
    "y": 122
},
"36378": {
    "visible": 1,
    "x": 920,
    "y": 125
},
"36380": {
    "visible": 1,
    "x": 924,
    "y": 133
},
"36381": {
    "visible": 1,
    "x": 932,
    "y": 139
},
"36382": {
    "visible": 1,
    "x": 935,
    "y": 148
},
"36383": {
    "visible": 1,
    "x": 939,
    "y": 161
},
"36384": {
    "visible": 1,
    "x": 939,
    "y": 163
},
"36385": {
    "visible": 1,
    "x": 941,
    "y": 172
},
"36386": {
    "visible": 1,
    "x": 943,
    "y": 187
},
"36387": {
    "visible": 1,
    "x": 947,
    "y": 204
},
"36388": {
    "visible": 1,
    "x": 950,
    "y": 223
},
"36389": {
    "visible": 1,
    "x": 952,
    "y": 242
},
"36390": {
    "visible": 1,
    "x": 952,
    "y": 242
},
"36391": {
    "visible": 1,
    "x": 954,
    "y": 262
},
"36392": {
    "visible": 1,
    "x": 954,
    "y": 285
},
"36393": {
    "visible": 1,
    "x": 956,
    "y": 309
},
"36394": {
    "visible": 1,
    "x": 958,
    "y": 335
},
"36395": {
    "visible": 1,
    "x": 958,
    "y": 358
},
"36396": {
    "visible": 1,
    "x": 958,
    "y": 358
},
"36397": {
    "visible": 1,
    "x": 978,
    "y": 382
},
"36398": {
    "visible": 1,
    "x": 999,
    "y": 406
},
"36399": {
    "visible": 1,
    "x": 1019,
    "y": 423
},
"36400": {
    "visible": 1,
    "x": 1040,
    "y": 431
},
"36401": {
    "visible": 1,
    "x": 1061,
    "y": 433
},
"36402": {
    "visible": 1,
    "x": 1079,
    "y": 423
},
"36403": {
    "visible": 1,
    "x": 1097,
    "y": 414
},
"36404": {
    "visible": 1,
    "x": 1129,
    "y": 409
},
"36405": {
    "visible": 1,
    "x": 1149,
    "y": 405
},
"36406": {
    "visible": 1,
    "x": 1166,
    "y": 401
},
"36407": {
    "visible": 1,
    "x": 1179,
    "y": 403
},
"36408": {
    "visible": 1,
    "x": 1181,
    "y": 403
},
"36409": {
    "visible": 1,
    "x": 1194,
    "y": 405
},
"36410": {
    "visible": 1,
    "x": 1202,
    "y": 407
},
"36411": {
    "visible": 1,
    "x": 1211,
    "y": 412
},
"36412": {
    "visible": 1,
    "x": 1220,
    "y": 420
},
"36413": {
    "visible": 1,
    "x": 1228,
    "y": 426
},
"36414": {
    "visible": 1,
    "x": 1230,
    "y": 427
},
"36415": {
    "visible": 1,
    "x": 1235,
    "y": 433
},
"36416": {
    "visible": 1,
    "x": 1241,
    "y": 444
},
"36417": {
    "visible": 1,
    "x": 1247,
    "y": 446
},
"36418": {
    "visible": 1,
    "x": 1251,
    "y": 439
},
"36419": {
    "visible": 1,
    "x": 1256,
    "y": 435
},
"36420": {
    "visible": 1,
    "x": 1254,
    "y": 431
},
"36421": {
    "visible": 1,
    "x": 1256,
    "y": 427
},
"36422": {
    "visible": 1,
    "x": 1258,
    "y": 424
},
"36423": {
    "visible": 1,
    "x": 1260,
    "y": 422
},
"36424": {
    "visible": 1,
    "x": 1262,
    "y": 422
},
"36425": {
    "visible": 1,
    "x": 1264,
    "y": 420
},
"36426": {
    "visible": 1,
    "x": 1262,
    "y": 420
},
"36427": {
    "visible": 1,
    "x": 1264,
    "y": 414
},
"36428": {
    "visible": 1,
    "x": 1267,
    "y": 414
},
"36429": {
    "visible": 1,
    "x": 1269,
    "y": 412
},
"36430": {
    "visible": 1,
    "x": 1269,
    "y": 412
},
"36431": {
    "visible": 1,
    "x": 1273,
    "y": 409
},
"36432": {
    "visible": 1,
    "x": 1273,
    "y": 409
},
"36433": {
    "visible": 1,
    "x": 1275,
    "y": 409
},
"36434": {
    "visible": 1,
    "x": 1277,
    "y": 407
},
"36435": {
    "visible": 1,
    "x": 1277,
    "y": 407
},
"36436": {
    "visible": 1,
    "x": 1277,
    "y": 407
},
"36437": {
    "visible": 1,
    "x": 1277,
    "y": 407
},
"36438": {
    "visible": 1,
    "x": 1277,
    "y": 407
},
"36439": {
    "visible": 1,
    "x": 1277,
    "y": 407
},
"36440": {
    "visible": 1,
    "x": 1279,
    "y": 407
},
"36441": {
    "visible": 1,
    "x": 1280,
    "y": 405
},
"36442": {
    "visible": 1,
    "x": 1280,
    "y": 407
},
"36443": {
    "visible": 1,
    "x": 1280,
    "y": 405
},
"36444": {
    "visible": 1,
    "x": 1280,
    "y": 405
},
"36445": {
    "visible": 1,
    "x": 1277,
    "y": 405
},
"36446": {
    "visible": 1,
    "x": 1279,
    "y": 405
},
"36447": {
    "visible": 1,
    "x": 1279,
    "y": 405
},
"36448": {
    "visible": 1,
    "x": 1277,
    "y": 405
},
"36449": {
    "visible": 1,
    "x": 1277,
    "y": 407
},
"36450": {
    "visible": 1,
    "x": 1277,
    "y": 407
},
"36451": {
    "visible": 1,
    "x": 1277,
    "y": 407
},
"36452": {
    "visible": 1,
    "x": 1277,
    "y": 403
},
"36453": {
    "visible": 1,
    "x": 1277,
    "y": 403
},
"36454": {
    "visible": 1,
    "x": 1277,
    "y": 405
},
"36455": {
    "visible": 1,
    "x": 1277,
    "y": 403
},
"36456": {
    "visible": 1,
    "x": 1277,
    "y": 403
},
"36457": {
    "visible": 1,
    "x": 1277,
    "y": 403
},
"36458": {
    "visible": 1,
    "x": 1277,
    "y": 403
},
"36459": {
    "visible": 1,
    "x": 1277,
    "y": 403
},
"36460": {
    "visible": 1,
    "x": 1277,
    "y": 405
},
"36461": {
    "visible": 1,
    "x": 1277,
    "y": 403
},
"36462": {
    "visible": 1,
    "x": 1277,
    "y": 403
},
"36463": {
    "visible": 1,
    "x": 1277,
    "y": 403
},
"36464": {
    "visible": 1,
    "x": 1277,
    "y": 403
},
"36465": {
    "visible": 1,
    "x": 1277,
    "y": 403
},
"36466": {
    "visible": 1,
    "x": 1277,
    "y": 403
},
"36467": {
    "visible": 1,
    "x": 1277,
    "y": 403
},
"36468": {
    "visible": 1,
    "x": 1277,
    "y": 403
},
"36469": {
    "visible": 1,
    "x": 1277,
    "y": 405
},
"36470": {
    "visible": 1,
    "x": 1275,
    "y": 405
},
"36471": {
    "visible": 1,
    "x": 1277,
    "y": 405
},
"36472": {
    "visible": 1,
    "x": 1277,
    "y": 407
},
"37341": {
    "visible": 1,
    "x": 1277,
    "y": 407
},
"37342": {
    "visible": 1,
    "x": 1277,
    "y": 407
},
"37343": {
    "visible": 1,
    "x": 1277,
    "y": 407
},
"37344": {
    "visible": 1,
    "x": 1277,
    "y": 407
},
"37345": {
    "visible": 1,
    "x": 1277,
    "y": 407
},
"37346": {
    "visible": 1,
    "x": 1277,
    "y": 407
},
"37347": {
    "visible": 1,
    "x": 1277,
    "y": 407
},
"37348": {
    "visible": 1,
    "x": 1277,
    "y": 407
},
"37349": {
    "visible": 1,
    "x": 1277,
    "y": 407
},
"37350": {
    "visible": 1,
    "x": 1277,
    "y": 407
},
"37351": {
    "visible": 1,
    "x": 1277,
    "y": 407
},
"37352": {
    "visible": 1,
    "x": 1277,
    "y": 407
},
"37353": {
    "visible": 1,
    "x": 1277,
    "y": 407
},
"37354": {
    "visible": 1,
    "x": 1277,
    "y": 407
}
}